hbrkga/__init__.py
hbrkga/data_utils.py
hbrkga/exploitation_method_BO.py
hbrkga/exploitation_method_BO_only_elites.py
hbrkga/exploitation_method_random_search.py
hbrkga/main-BO-only-elites.py
hbrkga/main-BO.py
hbrkga/main-randomwalk.py
hbrkga/nn_decoder_PT.py
hbrkga/nn_instance_PT.py
hbrkga/test.py
skga/__init__.py
skga/adaptee.py
skga/main.py
skga/hbrkga/__init__.py
skga/hbrkga/data_utils.py
skga/hbrkga/exploitation_method_BO.py
skga/hbrkga/exploitation_method_BO_only_elites.py
skga/hbrkga/exploitation_method_random_search.py
skga/hbrkga/main-BO-only-elites.py
skga/hbrkga/main-BO.py
skga/hbrkga/main-randomwalk.py
skga/hbrkga/nn_decoder_PT.py
skga/hbrkga/nn_instance_PT.py
skga/hbrkga/test.py
skga/hbrkga/brkga_mp_ipr/__init__.py
skga/hbrkga/brkga_mp_ipr/algorithm.py
skga/hbrkga/brkga_mp_ipr/enums.py
skga/hbrkga/brkga_mp_ipr/exceptions.py
skga/hbrkga/brkga_mp_ipr/exploitation_method.py
skga/hbrkga/brkga_mp_ipr/types.py
skga/hbrkga/brkga_mp_ipr/types_io.py
skga-1.0.0.dist-info/LICENSE
skga-1.0.0.dist-info/METADATA
skga-1.0.0.dist-info/WHEEL
skga-1.0.0.dist-info/top_level.txt
skga-1.0.0.dist-info/RECORD
